Workbook

Sheet Sales Data
A1: Order Date | B1: Order ID | C1: Region | D1: Category | E1: Product | F1: Units | G1: Unit Price | H1: Discount | I1: Revenue | J1: Cost | K1: Profit | L1: Channel | M1: Customer Segment | N1: Sales Rep
A2: 45292 | B2: ORD-01046 | C2: West | D2: Accessories | E2: Flow Mouse | F2: 4 | G2: 65.93 | H2: 0.1 | I2: =F2*G2*(1-H2) -> 237.348 | J2: 110.76 | K2: =I2-J2 -> 126.588 | L2: Online | M2: Mid-Market | N2: Noah Williams
A3: 45292 | B3: ORD-01446 | C3: South | D3: Accessories | E3: Arc Keyboard | F3: 8 | G3: 125.87 | H3: 0.03 | I3: =F3*G3*(1-H3) -> 976.7512 | J3: 463.2 | K3: =I3-J3 -> 513.5512 | L3: Partner | M3: SMB | N3: Liam Garcia
A4: 45293 | B4: ORD-00779 | C4: South | D4: Accessories | E4: Flow Mouse | F4: 7 | G4: 71.38 | H4: 0.12 | I4: =F4*G4*(1-H4) -> 439.7008 | J4: 209.86 | K4: =I4-J4 -> 229.8408 | L4: Retail | M4: Enterprise | N4: Ava Patel
A5: 45297 | B5: ORD-01120 | C5: North | D5: Office | E5: Lift Desk | F5: 7 | G5: 764.44 | H5: 0.12 | I5: =F5*G5*(1-H5) -> 4708.9504 | J5: 3264.16 | K5: =I5-J5 -> 1444.7904 | L5: Online | M5: Enterprise | N5: Sophia Brown
A6: 45298 | B6: ORD-00260 | C6: West | D6: Electronics | E6: Pulse Tablet | F6: 2 | G6: 618.69 | H6: 0.05 | I6: =F6*G6*(1-H6) -> 1175.511 | J6: 791.92 | K6: =I6-J6 -> 383.591 | L6: Retail | M6: SMB | N6: Ava Patel
A7: 45298 | B7: ORD-01429 | C7: East | D7: Accessories | E7: Arc Keyboard | F7: 6 | G7: 127.13 | H7: 0.05 | I7: =F7*G7*(1-H7) -> 724.641 | J7: 350.88 | K7: =I7-J7 -> 373.761 | L7: Partner | M7: Mid-Market | N7: Mia Chen
A8: 45299 | B8: ORD-00021 | C8: South | D8: Office | E8: Lift Desk | F8: 6 | G8: 792.31 | H8: 0.08 | I8: =F8*G8*(1-H8) -> 4373.5512 | J8: 2899.85 | K8: =I8-J8 -> 1473.7012 | L8: Online | M8: SMB | N8: Ava Patel
A9: 45299 | B9: ORD-00379 | C9: North | D9: Office | E9: Focus Lamp | F9: 8 | G9: 91.98 | H9: 0.03 | I9: =F9*G9*(1-H9) -> 713.7648 | J9: 353.2 | K9: =I9-J9 -> 360.5648 | L9: Online | M9: Enterprise | N9: Noah Williams
A10: 45303 | B10: ORD-01060 | C10: West | D10: Electronics | E10: Nova Laptop | F10: 7 | G10: 1148.34 | H10: 0.03 | I10: =F10*G10*(1-H10) -> 7797.2286 | J10: 5466.1 | K10: =I10-J10 -> 2331.1286 | L10: Partner | M10: Enterprise | N10: Ethan Davis
A11: 45304 | B11: ORD-00584 | C11: East | D11: Electronics | E11: Orbit Monitor | F11: 6 | G11: 363.96 | H11: 0.03 | I11: =F11*G11*(1-H11) -> 2118.2472 | J11: 1310.26 | K11: =I11-J11 -> 807.9872 | L11: Online | M11: Enterprise | N11: Ethan Davis
A12: 45304 | B12: ORD-01064 | C12: West | D12: Accessories | E12: Arc Keyboard | F12: 3 | G12: 124.77 | H12: 0.05 | I12: =F12*G12*(1-H12) -> 355.5945 | J12: 172.18 | K12: =I12-J12 -> 183.4145 | L12: Partner | M12: Mid-Market | N12: Ethan Davis
A13: 45304 | B13: ORD-01228 | C13: East | D13: Electronics | E13: Nova Laptop | F13: 6 | G13: 1150.37 | H13: 0.03 | I13: =F13*G13*(1-H13) -> 6695.1534 | J13: 4693.51 | K13: =I13-J13 -> 2001.6434 | L13: Partner | M13: Mid-Market | N13: Liam Garcia
... A1451: 46387 | B1451: ORD-01445 | C1451: East | D1451: Accessories | E1451: Flow Mouse | F1451: 16 | G1451: 78.61 | H1451: 0.1 | I1451: =F1451*G1451*(1-H1451) -> 1131.984 | J1451: 528.26 | K1451: =I1451-J1451 -> 603.724 | L1451: Partner | M1451: Enterprise | N1451: Ethan Davis

Sheet Analysis
A1: Formula-Driven Analysis Engine
A3: Selected Year | B3: =Dashboard!C5 -> 2026 | D3: KPI | E3: Value | G3: Product | H3: Revenue | J3: Region | K3: Revenue | M3: Category | N3: Revenue
A4: Selected Region | B4: =Dashboard!H5 -> All | D4: Total Revenue | E4: =SUMIFS('Sales Data'!$I$2:$I$1451,'Sales Data'!$A$2:$A$1451,">="&DATE($B$3,1,1),'Sales Data'!$A$2:$A$1451,"<"&DATE($B$3+1,1,1),'Sales Data'!$C$2:$C$1451,IF($B$4="All","*",$B$4),'Sales Data'!$D$2:$D$1451,IF($B$5="All","*",$B$5)) -> 1468806.5 | G4: Nova Laptop | H4: =SUMIFS('Sales Data'!$I$2:$I$1451,'Sales Data'!$E$2:$E$1451,G4,'Sales Data'!$A$2:$A$1451,">="&DATE($B$3,1,1),'Sales Data'!$A$2:$A$1451,"<"&DATE($B$3+1,1,1),'Sales Data'!$C$2:$C$1451,IF($B$4="All","*",$B$4),'Sales Data'!$D$2:$D$1451,IF($B$5="All","*",$B$5)) -> 417500.23 | J4: North | K4: =SUMIFS('Sales Data'!$I$2:$I$1451,'Sales Data'!$C$2:$C$1451,J4,'Sales Data'!$A$2:$A$1451,">="&DATE($B$3,1,1),'Sales Data'!$A$2:$A$1451,"<"&DATE($B$3+1,1,1),'Sales Data'!$D$2:$D$1451,IF($B$5="All","*",$B$5)) -> 324160.11 | M4: Electronics | N4: =SUMIFS('Sales Data'!$I$2:$I$1451,'Sales Data'!$D$2:$D$1451,M4,'Sales Data'!$A$2:$A$1451,">="&DATE($B$3,1,1),'Sales Data'!$A$2:$A$1451,"<"&DATE($B$3+1,1,1),'Sales Data'!$C$2:$C$1451,IF($B$4="All","*",$B$4)) -> 836913.19
A5: Selected Category | B5: =Dashboard!N5 -> All | D5: Total Profit | E5: =SUMIFS('Sales Data'!$K$2:$K$1451,'Sales Data'!$A$2:$A$1451,">="&DATE($B$3,1,1),'Sales Data'!$A$2:$A$1451,"<"&DATE($B$3+1,1,1),'Sales Data'!$C$2:$C$1451,IF($B$4="All","*",$B$4),'Sales Data'!$D$2:$D$1451,IF($B$5="All","*",$B$5)) -> 499422.11 | G5: Pulse Tablet | H5: =SUMIFS('Sales Data'!$I$2:$I$1451,'Sales Data'!$E$2:$E$1451,G5,'Sales Data'!$A$2:$A$1451,">="&DATE($B$3,1,1),'Sales Data'!$A$2:$A$1451,"<"&DATE($B$3+1,1,1),'Sales Data'!$C$2:$C$1451,IF($B$4="All","*",$B$4),'Sales Data'!$D$2:$D$1451,IF($B$5="All","*",$B$5)) -> 270162.37 | J5: South | K5: =SUMIFS('Sales Data'!$I$2:$I$1451,'Sales Data'!$C$2:$C$1451,J5,'Sales Data'!$A$2:$A$1451,">="&DATE($B$3,1,1),'Sales Data'!$A$2:$A$1451,"<"&DATE($B$3+1,1,1),'Sales Data'!$D$2:$D$1451,IF($B$5="All","*",$B$5)) -> 429048.26 | M5: Office | N5: =SUMIFS('Sales Data'!$I$2:$I$1451,'Sales Data'!$D$2:$D$1451,M5,'Sales Data'!$A$2:$A$1451,">="&DATE($B$3,1,1),'Sales Data'!$A$2:$A$1451,"<"&DATE($B$3+1,1,1),'Sales Data'!$C$2:$C$1451,IF($B$4="All","*",$B$4)) -> 564689.73
A6: Last Refresh | B6: 46197 | D6: Profit Margin | E6: =IFERROR(E5/E4,0) -> 0.340019 | G6: Orbit Monitor | H6: =SUMIFS('Sales Data'!$I$2:$I$1451,'Sales Data'!$E$2:$E$1451,G6,'Sales Data'!$A$2:$A$1451,">="&DATE($B$3,1,1),'Sales Data'!$A$2:$A$1451,"<"&DATE($B$3+1,1,1),'Sales Data'!$C$2:$C$1451,IF($B$4="All","*",$B$4),'Sales Data'!$D$2:$D$1451,IF($B$5="All","*",$B$5)) -> 149250.59 | J6: East | K6: =SUMIFS('Sales Data'!$I$2:$I$1451,'Sales Data'!$C$2:$C$1451,J6,'Sales Data'!$A$2:$A$1451,">="&DATE($B$3,1,1),'Sales Data'!$A$2:$A$1451,"<"&DATE($B$3+1,1,1),'Sales Data'!$D$2:$D$1451,IF($B$5="All","*",$B$5)) -> 338322.29 | M6: Accessories | N6: =SUMIFS('Sales Data'!$I$2:$I$1451,'Sales Data'!$D$2:$D$1451,M6,'Sales Data'!$A$2:$A$1451,">="&DATE($B$3,1,1),'Sales Data'!$A$2:$A$1451,"<"&DATE($B$3+1,1,1),'Sales Data'!$C$2:$C$1451,IF($B$4="All","*",$B$4)) -> 67203.531
D7: Orders | E7: =COUNTIFS('Sales Data'!$A$2:$A$1451,">="&DATE($B$3,1,1),'Sales Data'!$A$2:$A$1451,"<"&DATE($B$3+1,1,1),'Sales Data'!$C$2:$C$1451,IF($B$4="All","*",$B$4),'Sales Data'!$D$2:$D$1451,IF($B$5="All","*",$B$5),'Sales Data'!$B$2:$B$1451,"<>") -> 475 | G7: Ergo Chair | H7: =SUMIFS('Sales Data'!$I$2:$I$1451,'Sales Data'!$E$2:$E$1451,G7,'Sales Data'!$A$2:$A$1451,">="&DATE($B$3,1,1),'Sales Data'!$A$2:$A$1451,"<"&DATE($B$3+1,1,1),'Sales Data'!$C$2:$C$1451,IF($B$4="All","*",$B$4),'Sales Data'!$D$2:$D$1451,IF($B$5="All","*",$B$5)) -> 170809.48 | J7: West | K7: =SUMIFS('Sales Data'!$I$2:$I$1451,'Sales Data'!$C$2:$C$1451,J7,'Sales Data'!$A$2:$A$1451,">="&DATE($B$3,1,1),'Sales Data'!$A$2:$A$1451,"<"&DATE($B$3+1,1,1),'Sales Data'!$D$2:$D$1451,IF($B$5="All","*",$B$5)) -> 377275.8
D8: Average Order Value | E8: =IFERROR(E4/E7,0) -> 3092.2241 | G8: Lift Desk | H8: =SUMIFS('Sales Data'!$I$2:$I$1451,'Sales Data'!$E$2:$E$1451,G8,'Sales Data'!$A$2:$A$1451,">="&DATE($B$3,1,1),'Sales Data'!$A$2:$A$1451,"<"&DATE($B$3+1,1,1),'Sales Data'!$C$2:$C$1451,IF($B$4="All","*",$B$4),'Sales Data'!$D$2:$D$1451,IF($B$5="All","*",$B$5)) -> 351456.73
A9: Month | B9: Revenue | C9: Profit | D9: YoY Revenue Growth | E9: =IFERROR(E4/SUMIFS('Sales Data'!$I$2:$I$1451,'Sales Data'!$A$2:$A$1451,">="&DATE($B$3-1,1,1),'Sales Data'!$A$2:$A$1451,"<"&DATE($B$3,1,1),'Sales Data'!$C$2:$C$1451,IF($B$4="All","*",$B$4),'Sales Data'!$D$2:$D$1451,IF($B$5="All","*",$B$5))-1,0) -> 0.16429042 | G9: Focus Lamp | H9: =SUMIFS('Sales Data'!$I$2:$I$1451,'Sales Data'!$E$2:$E$1451,G9,'Sales Data'!$A$2:$A$1451,">="&DATE($B$3,1,1),'Sales Data'!$A$2:$A$1451,"<"&DATE($B$3+1,1,1),'Sales Data'!$C$2:$C$1451,IF($B$4="All","*",$B$4),'Sales Data'!$D$2:$D$1451,IF($B$5="All","*",$B$5)) -> 42423.526
A10: =TEXT(DATE($B$3,1,1),"mmm") -> Jan | B10: =SUMIFS('Sales Data'!$I$2:$I$1451,'Sales Data'!$A$2:$A$1451,">="&DATE($B$3,1,1),'Sales Data'!$A$2:$A$1451,"<"&DATE($B$3,2,1),'Sales Data'!$C$2:$C$1451,IF($B$4="All","*",$B$4),'Sales Data'!$D$2:$D$1451,IF($B$5="All","*",$B$5)) -> 146158.77 | C10: =SUMIFS('Sales Data'!$K$2:$K$1451,'Sales Data'!$A$2:$A$1451,">="&DATE($B$3,1,1),'Sales Data'!$A$2:$A$1451,"<"&DATE($B$3,2,1),'Sales Data'!$C$2:$C$1451,IF($B$4="All","*",$B$4),'Sales Data'!$D$2:$D$1451,IF($B$5="All","*",$B$5)) -> 48450.682 | G10: Arc Keyboard | H10: =SUMIFS('Sales Data'!$I$2:$I$1451,'Sales Data'!$E$2:$E$1451,G10,'Sales Data'!$A$2:$A$1451,">="&DATE($B$3,1,1),'Sales Data'!$A$2:$A$1451,"<"&DATE($B$3+1,1,1),'Sales Data'!$C$2:$C$1451,IF($B$4="All","*",$B$4),'Sales Data'!$D$2:$D$1451,IF($B$5="All","*",$B$5)) -> 38463.73
A11: =TEXT(DATE($B$3,2,1),"mmm") -> Feb | B11: =SUMIFS('Sales Data'!$I$2:$I$1451,'Sales Data'!$A$2:$A$1451,">="&DATE($B$3,2,1),'Sales Data'!$A$2:$A$1451,"<"&DATE($B$3,3,1),'Sales Data'!$C$2:$C$1451,IF($B$4="All","*",$B$4),'Sales Data'!$D$2:$D$1451,IF($B$5="All","*",$B$5)) -> 117455.08 | C11: =SUMIFS('Sales Data'!$K$2:$K$1451,'Sales Data'!$A$2:$A$1451,">="&DATE($B$3,2,1),'Sales Data'!$A$2:$A$1451,"<"&DATE($B$3,3,1),'Sales Data'!$C$2:$C$1451,IF($B$4="All","*",$B$4),'Sales Data'!$D$2:$D$1451,IF($B$5="All","*",$B$5)) -> 38688.503 | G11: Flow Mouse | H11: =SUMIFS('Sales Data'!$I$2:$I$1451,'Sales Data'!$E$2:$E$1451,G11,'Sales Data'!$A$2:$A$1451,">="&DATE($B$3,1,1),'Sales Data'!$A$2:$A$1451,"<"&DATE($B$3+1,1,1),'Sales Data'!$C$2:$C$1451,IF($B$4="All","*",$B$4),'Sales Data'!$D$2:$D$1451,IF($B$5="All","*",$B$5)) -> 28739.801
A12: =TEXT(DATE($B$3,3,1),"mmm") -> Mar | B12: =SUMIFS('Sales Data'!$I$2:$I$1451,'Sales Data'!$A$2:$A$1451,">="&DATE($B$3,3,1),'Sales Data'!$A$2:$A$1451,"<"&DATE($B$3,4,1),'Sales Data'!$C$2:$C$1451,IF($B$4="All","*",$B$4),'Sales Data'!$D$2:$D$1451,IF($B$5="All","*",$B$5)) -> 131681.58 | C12: =SUMIFS('Sales Data'!$K$2:$K$1451,'Sales Data'!$A$2:$A$1451,">="&DATE($B$3,3,1),'Sales Data'!$A$2:$A$1451,"<"&DATE($B$3,4,1),'Sales Data'!$C$2:$C$1451,IF($B$4="All","*",$B$4),'Sales Data'!$D$2:$D$1451,IF($B$5="All","*",$B$5)) -> 47774.583
A13: =TEXT(DATE($B$3,4,1),"mmm") -> Apr | B13: =SUMIFS('Sales Data'!$I$2:$I$1451,'Sales Data'!$A$2:$A$1451,">="&DATE($B$3,4,1),'Sales Data'!$A$2:$A$1451,"<"&DATE($B$3,5,1),'Sales Data'!$C$2:$C$1451,IF($B$4="All","*",$B$4),'Sales Data'!$D$2:$D$1451,IF($B$5="All","*",$B$5)) -> 127291.48 | C13: =SUMIFS('Sales Data'!$K$2:$K$1451,'Sales Data'!$A$2:$A$1451,">="&DATE($B$3,4,1),'Sales Data'!$A$2:$A$1451,"<"&DATE($B$3,5,1),'Sales Data'!$C$2:$C$1451,IF($B$4="All","*",$B$4),'Sales Data'!$D$2:$D$1451,IF($B$5="All","*",$B$5)) -> 44835.223
A14: =TEXT(DATE($B$3,5,1),"mmm") -> May | B14: =SUMIFS('Sales Data'!$I$2:$I$1451,'Sales Data'!$A$2:$A$1451,">="&DATE($B$3,5,1),'Sales Data'!$A$2:$A$1451,"<"&DATE($B$3,6,1),'Sales Data'!$C$2:$C$1451,IF($B$4="All","*",$B$4),'Sales Data'!$D$2:$D$1451,IF($B$5="All","*",$B$5)) -> 156998.89 | C14: =SUMIFS('Sales Data'!$K$2:$K$1451,'Sales Data'!$A$2:$A$1451,">="&DATE($B$3,5,1),'Sales Data'!$A$2:$A$1451,"<"&DATE($B$3,6,1),'Sales Data'!$C$2:$C$1451,IF($B$4="All","*",$B$4),'Sales Data'!$D$2:$D$1451,IF($B$5="All","*",$B$5)) -> 56273.987
A15: =TEXT(DATE($B$3,6,1),"mmm") -> Jun | B15: =SUMIFS('Sales Data'!$I$2:$I$1451,'Sales Data'!$A$2:$A$1451,">="&DATE($B$3,6,1),'Sales Data'!$A$2:$A$1451,"<"&DATE($B$3,7,1),'Sales Data'!$C$2:$C$1451,IF($B$4="All","*",$B$4),'Sales Data'!$D$2:$D$1451,IF($B$5="All","*",$B$5)) -> 65061.122 | C15: =SUMIFS('Sales Data'!$K$2:$K$1451,'Sales Data'!$A$2:$A$1451,">="&DATE($B$3,6,1),'Sales Data'!$A$2:$A$1451,"<"&DATE($B$3,7,1),'Sales Data'!$C$2:$C$1451,IF($B$4="All","*",$B$4),'Sales Data'!$D$2:$D$1451,IF($B$5="All","*",$B$5)) -> 23778.362
A16: =TEXT(DATE($B$3,7,1),"mmm") -> Jul | B16: =SUMIFS('Sales Data'!$I$2:$I$1451,'Sales Data'!$A$2:$A$1451,">="&DATE($B$3,7,1),'Sales Data'!$A$2:$A$1451,"<"&DATE($B$3,8,1),'Sales Data'!$C$2:$C$1451,IF($B$4="All","*",$B$4),'Sales Data'!$D$2:$D$1451,IF($B$5="All","*",$B$5)) -> 92694.5 | C16: =SUMIFS('Sales Data'!$K$2:$K$1451,'Sales Data'!$A$2:$A$1451,">="&DATE($B$3,7,1),'Sales Data'!$A$2:$A$1451,"<"&DATE($B$3,8,1),'Sales Data'!$C$2:$C$1451,IF($B$4="All","*",$B$4),'Sales Data'!$D$2:$D$1451,IF($B$5="All","*",$B$5)) -> 31707.64
A17: =TEXT(DATE($B$3,8,1),"mmm") -> Aug | B17: =SUMIFS('Sales Data'!$I$2:$I$1451,'Sales Data'!$A$2:$A$1451,">="&DATE($B$3,8,1),'Sales Data'!$A$2:$A$1451,"<"&DATE($B$3,9,1),'Sales Data'!$C$2:$C$1451,IF($B$4="All","*",$B$4),'Sales Data'!$D$2:$D$1451,IF($B$5="All","*",$B$5)) -> 105609.78 | C17: =SUMIFS('Sales Data'!$K$2:$K$1451,'Sales Data'!$A$2:$A$1451,">="&DATE($B$3,8,1),'Sales Data'!$A$2:$A$1451,"<"&DATE($B$3,9,1),'Sales Data'!$C$2:$C$1451,IF($B$4="All","*",$B$4),'Sales Data'!$D$2:$D$1451,IF($B$5="All","*",$B$5)) -> 35635.685
A18: =TEXT(DATE($B$3,9,1),"mmm") -> Sep | B18: =SUMIFS('Sales Data'!$I$2:$I$1451,'Sales Data'!$A$2:$A$1451,">="&DATE($B$3,9,1),'Sales Data'!$A$2:$A$1451,"<"&DATE($B$3,10,1),'Sales Data'!$C$2:$C$1451,IF($B$4="All","*",$B$4),'Sales Data'!$D$2:$D$1451,IF($B$5="All","*",$B$5)) -> 66644.398 | C18: =SUMIFS('Sales Data'!$K$2:$K$1451,'Sales Data'!$A$2:$A$1451,">="&DATE($B$3,9,1),'Sales Data'!$A$2:$A$1451,"<"&DATE($B$3,10,1),'Sales Data'!$C$2:$C$1451,IF($B$4="All","*",$B$4),'Sales Data'!$D$2:$D$1451,IF($B$5="All","*",$B$5)) -> 23564.998
A19: =TEXT(DATE($B$3,10,1),"mmm") -> Oct | B19: =SUMIFS('Sales Data'!$I$2:$I$1451,'Sales Data'!$A$2:$A$1451,">="&DATE($B$3,10,1),'Sales Data'!$A$2:$A$1451,"<"&DATE($B$3,11,1),'Sales Data'!$C$2:$C$1451,IF($B$4="All","*",$B$4),'Sales Data'!$D$2:$D$1451,IF($B$5="All","*",$B$5)) -> 137538.74 | C19: =SUMIFS('Sales Data'!$K$2:$K$1451,'Sales Data'!$A$2:$A$1451,">="&DATE($B$3,10,1),'Sales Data'!$A$2:$A$1451,"<"&DATE($B$3,11,1),'Sales Data'!$C$2:$C$1451,IF($B$4="All","*",$B$4),'Sales Data'!$D$2:$D$1451,IF($B$5="All","*",$B$5)) -> 43637.291
A20: =TEXT(DATE($B$3,11,1),"mmm") -> Nov | B20: =SUMIFS('Sales Data'!$I$2:$I$1451,'Sales Data'!$A$2:$A$1451,">="&DATE($B$3,11,1),'Sales Data'!$A$2:$A$1451,"<"&DATE($B$3,12,1),'Sales Data'!$C$2:$C$1451,IF($B$4="All","*",$B$4),'Sales Data'!$D$2:$D$1451,IF($B$5="All","*",$B$5)) -> 126808.92 | C20: =SUMIFS('Sales Data'!$K$2:$K$1451,'Sales Data'!$A$2:$A$1451,">="&DATE($B$3,11,1),'Sales Data'!$A$2:$A$1451,"<"&DATE($B$3,12,1),'Sales Data'!$C$2:$C$1451,IF($B$4="All","*",$B$4),'Sales Data'!$D$2:$D$1451,IF($B$5="All","*",$B$5)) -> 41053.274
A21: =TEXT(DATE($B$3,12,1),"mmm") -> Dec | B21: =SUMIFS('Sales Data'!$I$2:$I$1451,'Sales Data'!$A$2:$A$1451,">="&DATE($B$3,12,1),'Sales Data'!$A$2:$A$1451,"<"&DATE($B$3,13,1),'Sales Data'!$C$2:$C$1451,IF($B$4="All","*",$B$4),'Sales Data'!$D$2:$D$1451,IF($B$5="All","*",$B$5)) -> 194863.19 | C21: =SUMIFS('Sales Data'!$K$2:$K$1451,'Sales Data'!$A$2:$A$1451,">="&DATE($B$3,12,1),'Sales Data'!$A$2:$A$1451,"<"&DATE($B$3,13,1),'Sales Data'!$C$2:$C$1451,IF($B$4="All","*",$B$4),'Sales Data'!$D$2:$D$1451,IF($B$5="All","*",$B$5)) -> 64021.879

Sheet Dashboard
A1: SALES & REVENUE ANALYSIS
A3: Interactive performance view • Update the blue selectors to refresh every KPI and chart
A5: YEAR | C5: 2026 | F5: REGION | H5: All | L5: CATEGORY | N5: All
A7: TOTAL REVENUE | D7: TOTAL PROFIT | G7: PROFIT MARGIN | J7: ORDERS | M7: YOY REVENUE GROWTH
A9: =Analysis!E4 -> 1468806.5 | D9: =Analysis!E5 -> 499422.11 | G9: =Analysis!E6 -> 0.340019 | J9: =Analysis!E7 -> 475 | M9: =Analysis!E9 -> 0.16429042
A12: Monthly Revenue & Profit | K12: Revenue by Region
A29: Product Performance | I29: Category Mix
A49: ="Source: Sales Data tab | Refreshed: "&TEXT(Analysis!B6,"yyyy-mm-dd")&" | Tip: paste replacement rows into the Sales Data table and extend formulas in Revenue and Profit." -> Source: Sales Data tab | Refreshed: 2026-06-24 | Tip: paste replacement rows into the Sales Data table and extend formulas in Revenue and Profit.
